p3dss/__init__.py
p3dss/exceptions.py
p3dss/nodes.py
p3dss/processor.py
p3dss/types.py
p3dss-0.5.0.dist-info/LICENSE
p3dss-0.5.0.dist-info/METADATA
p3dss-0.5.0.dist-info/WHEEL
p3dss-0.5.0.dist-info/top_level.txt
p3dss-0.5.0.dist-info/RECORD
