Metadata-Version: 2.1
Name: p3dss
Version: 0.5.0
Summary: p3dss - the spritesheet handling library for Panda3D
Home-page: https://github.com/moonburnt/p3dss
Author: moonburnt
Author-email: moonburnt@disroot.org
License: MIT
Platform: UNKNOWN
Classifier: Programming Language :: Python :: 3
License-File: LICENSE
Requires-Dist: panda3d (>=1.10)
